supacrawler/__init__.py
supacrawler/client.py
supacrawler/types.py
supacrawler/scraper_client/__init__.py
supacrawler/scraper_client/client.py
supacrawler/scraper_client/errors.py
supacrawler/scraper_client/py.typed
supacrawler/scraper_client/types.py
supacrawler/scraper_client/api/__init__.py
supacrawler/scraper_client/api/health/__init__.py
supacrawler/scraper_client/api/health/get_internal_health.py
supacrawler/scraper_client/api/jobs/__init__.py
supacrawler/scraper_client/api/jobs/get_v_1_crawl_job_id.py
supacrawler/scraper_client/api/jobs/post_v1_crawl.py
supacrawler/scraper_client/api/parse/__init__.py
supacrawler/scraper_client/api/parse/get_v1_parse_examples.py
supacrawler/scraper_client/api/parse/get_v1_parse_templates.py
supacrawler/scraper_client/api/parse/post_v1_parse.py
supacrawler/scraper_client/api/scrape/__init__.py
supacrawler/scraper_client/api/scrape/get_v1_scrape.py
supacrawler/scraper_client/api/screenshots/__init__.py
supacrawler/scraper_client/api/screenshots/get_v1_screenshots.py
supacrawler/scraper_client/api/screenshots/post_v1_screenshots.py
supacrawler/scraper_client/models/__init__.py
supacrawler/scraper_client/models/crawl_create_request.py
supacrawler/scraper_client/models/crawl_create_request_format.py
supacrawler/scraper_client/models/crawl_create_response.py
supacrawler/scraper_client/models/crawl_job_data.py
supacrawler/scraper_client/models/crawl_job_data_crawl_data.py
supacrawler/scraper_client/models/crawl_job_data_error_data.py
supacrawler/scraper_client/models/crawl_statistics.py
supacrawler/scraper_client/models/crawl_status_response.py
supacrawler/scraper_client/models/crawl_status_response_status.py
supacrawler/scraper_client/models/error.py
supacrawler/scraper_client/models/get_v1_scrape_format.py
supacrawler/scraper_client/models/page_content.py
supacrawler/scraper_client/models/page_metadata.py
supacrawler/scraper_client/models/parse_create_request.py
supacrawler_py-0.1.6.dist-info/METADATA
supacrawler_py-0.1.6.dist-info/WHEEL
supacrawler_py-0.1.6.dist-info/top_level.txt
supacrawler_py-0.1.6.dist-info/RECORD
