Metadata-Version: 2.4
Name: supacrawler-py
Version: 0.1.6
Summary: Typed Python SDK for Supacrawler API (scrape, jobs, screenshots, watch)
Author-email: Supacrawler <support@supacrawler.com>
License-Expression: MIT
Project-URL: Homepage, https://supacrawler.com
Project-URL: Repository, https://supacrawler.com
Requires-Python: >=3.9
Requires-Dist: dotenv>=0.9.9
Requires-Dist: httpx>=0.27.0
Requires-Dist: ipykernel>=6.30.1
Requires-Dist: pydantic>=2.6.0
Requires-Dist: attrs>=22.2.0
Requires-Dist: python-dateutil>=2.8.0
Provides-Extra: test
Requires-Dist: pytest>=7.0.0; extra == "test"
Requires-Dist: pytest-cov>=4.0.0; extra == "test"
